MANIFEST.in
README.rst
setup.py
yaddle/__init__.py
yaddle/tool.py
yaddle/yaddle.py
yaddle.egg-info/PKG-INFO
yaddle.egg-info/SOURCES.txt
yaddle.egg-info/dependency_links.txt
yaddle.egg-info/pbr.json
yaddle.egg-info/requires.txt
yaddle.egg-info/top_level.txt