Metadata-Version: 1.1
Name: yaddle
Version: 0.0.2
Summary: yet another data format description language
Home-page: https://github.com/zweifisch/yaddle-py
Author: Feng Zhou
Author-email: zf.pascal@gmail.com
License: MIT
Keywords: json schema
Platform: UNKNOWN
Classifier: Development Status :: 3 - Alpha
Classifier: Operating System :: OS Independent
Classifier: Intended Audience :: Developers
Classifier: License :: OSI Approved :: MIT License
Classifier: Programming Language :: Python :: 2.7
Classifier: Programming Language :: Python :: 3.4
